ocli/__init__.py
ocli/extra.py
ocli/test_parser2.py
ocli-1.0.0.dist-info/LICENSE
ocli-1.0.0.dist-info/METADATA
ocli-1.0.0.dist-info/WHEEL
ocli-1.0.0.dist-info/top_level.txt
ocli-1.0.0.dist-info/RECORD
