Metadata-Version: 2.1
Name: ocli
Version: 1.0.0
Summary: Command line app object
Home-page: https://github.com/biojet1/ocli
Author: biojet1
Author-email: biojet1@gmail.com
License: UNKNOWN
Platform: UNKNOWN
Classifier: Programming Language :: Python :: 3
Classifier: License :: OSI Approved :: MIT License
Classifier: Operating System :: OS Independent
Requires-Python: >=3.6
License-File: LICENSE
